teste_operacoes_lib/__init__.py
teste_operacoes_lib/operacoes.py
teste_operacoes-0.0.1.dist-info/METADATA
teste_operacoes-0.0.1.dist-info/WHEEL
teste_operacoes-0.0.1.dist-info/top_level.txt
teste_operacoes-0.0.1.dist-info/RECORD
