Metadata-Version: 2.1
Name: teste-operacoes
Version: 0.0.1
Summary: Um pacote Python simples para operações de teste.
Home-page: https://github.com/Rommanomm/teste_operacoes_project.git
Author: Rommano Moreira Mismetti
Author-email: rommanomm@gmail.com
Classifier: Programming Language :: Python :: 3
Classifier: License :: OSI Approved :: MIT License
Classifier: Operating System :: OS Independent
Classifier: Topic :: Software Development :: Testing
Classifier: Topic :: Utilities
Requires-Python: >=3.8
